{
    "name":"Skykomish",
    "latitude":47.667300,
	"longitude":-121.390171,
    "zoom":12,
    "parkings": [],
    "guides": [
        {
            "name": "Western Washington Bouldering",
            "link": "http://westernwashingtonbouldering.com/guidebook",
            "thumbnail": "https://m.media-amazon.com/images/I/A1xliUn6HJL._SL1500_.jpg"   
        }
    ],
    "country": "us",
    "state": "washington",
	"rock_type": "gnei",
	"overview": [
		"Located in Washington state, Skykomish is renowned for its pristine granite boulders set against the backdrop of the Cascade Mountains. With a reputation for diverse problems and a variety of holds, it's a popular spot for climbers. The best season is typically summer and fall when conditions are optimal for sending hard projects.",
		"Situado en el estado de Washington, Skykomish es famoso por sus bloques de granito impecables con las Montañas Cascade de fondo. Con una reputación por sus problemas variados y una variedad de agarres, es un lugar popular entre los escaladores. La mejor temporada suele ser el verano y el otoño, cuando las condiciones son óptimas para resolver proyectos difíciles."
	]
}