{
    "name": "Valcorchero",
    "latitude": 40.055890,
    "longitude": -6.098523,
    "zoom": 14,
    "parkings": [],
    "lins": [
        {
            "name": "Valcorchero Boulder Instagram",
            "link": "https://www.instagram.com/valcorchero_boulder/",
			"free": true
        }
    ],
    "guides": [
        {
            "name": "Valcorchero. Guia de Escalda en Bloque",
            "link": "https://www.libreriadesnivel.com/libros/valcorchero-guia-de-escalada-en-bloque/9788409309641/",
            "thumbnail": "https://www.libreriadesnivel.com/media/img/portadas/9788409309641.jpg"   
        },
        {
            "name": "Boulder en Espa\u00f1a",
            "link": [
              "https://amzn.to/3UizeG0", 
                "https://amzn.to/3SiGNuV"
            ],
            "thumbnail": "https://m.media-amazon.com/images/I/81UJX3rkGML._AC_UY218_.jpg"   
        }
    ],
    "country": "spain",
    "state": "extremadura",
	"rock_type": "gran",
	"overview": [
		"Valcorchero, in Spain, stands out for its unique granite rock. Located in Extremadura, this area offers a wide range of bouldering problems on distinctive rock formations. The best season is winter and spring. Valcorchero is appreciated for its uniqueness and is a popular destination among climbers and boulderers.",
		"alcorchero, en España, destaca por su granito único. Ubicado en Extremadura, este lugar ofrece una amplia gama de problemas de boulder en una formación de roca peculiar. La temporada óptima es el invierno y la primavera. Valcorchero es apreciado por su singularidad y es un destino popular entre escaladores y boulderers."
	]
}

