{
    "name": "Malniu",
    "latitude": 42.464154,
    "longitude": 1.784641,
    "zoom": 16,
    "parkings": [
        {
            "parking_latitude": 42.464127,
            "parking_longitude": 1.785602
        }
    ],
    "links": [
        {
            "name": "Ask for info in the refuge",
            "link": "http://www.refugimalniu.com/",
			"free": true
        },
        {
            "name": "General info, Blog",
            "link": "https://rotpunktholds.blogspot.com/search/label/Boulder%20en%20Malniu%20%28Meranges%29",
			"free": true
        }
    ],
    "country": "spain",
    "state": "catalonia",
	"rock_type": "gran",
	"overview": [
		"Malniu, located in the picturesque Pyrenees of Catalonia, is a bouldering destination known for its granite rock. Climbers visit Malniu for its alpine setting and diverse boulder problems, with a mix of crimps, slopers, and jugs. This area is favored in the summer when cooler mountain temperatures provide an escape from the heat.",
		"Malniu, situado en los pintorescos Pirineos de Cataluña, es un destino de boulder conocido por su roca de granito. Los escaladores visitan Malniu por su entorno alpino y problemas variados de boulder, que incluyen cantos, regletas y agarres grandes. Esta zona es especialmente popular en verano, cuando las temperaturas frescas de montaña ofrecen un respiro del calor."
	]
}