{
    "name": "Moe's Valley",
    "latitude": 37.06622,
    "longitude": -113.629762,
    "zoom": 15,
    "parkings": [
        {
            "parking_latitude": 37.069866,
            "parking_longitude": -113.625452
        }
    ],
    "guides": [
        {
            "name": "St. George Bouldering",
            "link": "http://stores.sharpendbooks.com/st-george-bouldering-includes-2-year-subscription-to-digital-edition-see-the-digital-page-for-complete-details/"
        },
        {
            "name": "27 Crags",
            "link": "https://27crags.com/crags/moe-s-valley"
        },
        {
            "name": "Mountain Project",
            "link": "https://www.mountainproject.com/area/106028834/moes-valley",
			"free": true
        }
    ],
    "country": "us"
}