{
    "name": "Sydney",
    "latitude": -33.864701,
    "longitude": 151.215742,
    "zoom": 13,
    "parkings": [],
    "guides": [
        {
            "name": "Sydney Bouldering Guide",
            "link": "https://www.climbinganchors.com.au/sydney-bouldering-guide",
            "thumbnail": "https://www.climbinganchors.com.au/assets/full/BOOKSBG.jpg?20230928120834"
        }
    ],
    "country": "au",
	"rock_type": "sand",
	"overview": [
		"Sydney, renowned for its stunning natural scenery, offers an exciting array of outdoor bouldering spots that cater to all skill levels. Areas like The Frontline, Lindfield Rocks, Queens Park, Sissy Crag, and Crumbly feature problems ranging from V0 to V15, providing a mix of beginner routes and expert challenges. Set within picturesque bushland and coastal settings, these bouldering sites allow climbers to enjoy the unique sandstone formations and scenic beauty Sydney has to offer. Climbers are reminded to respect the natural environment and the cultural heritage of these lands, making Sydney's outdoor bouldering experience both thrilling and respectful.",
		"Sydney, conocido por su impresionante escenario natural, ofrece una emocionante variedad de lugares para bouldering al aire libre que se adaptan a todos los niveles de habilidad. Áreas como The Frontline, Lindfield Rocks, Queens Park, Sissy Crag y Crumbly, con problemas desde V0 hasta V15, brindan una combinación de rutas para principiantes y desafíos para expertos. Ubicados en pintorescos entornos de matorrales y costas, estos sitios de bouldering permiten a los escaladores disfrutar de las formaciones únicas de arenisca y la belleza escénica que Sydney tiene para ofrecer. Se recuerda a los escaladores respetar el entorno natural y el patrimonio cultural de estas tierras, haciendo de la experiencia de bouldering al aire libre en Sydney algo emocionante y respetuoso."
	]
}

