{
    "name": "Buñol",
    "latitude": 39.417036,
    "longitude": -0.812299,
    "zoom": 14,
    "parkings": [],
    "guides": [
        {
            "name": "Guía Buñol Malacara",
            "link": "https://tangosenlaroca.com/1104-guia-bunol-malacara.html",
            "thumbnail": "https://tangosenlaroca.com/2443-thickbox_default/guia-bunol-malacara.jpg"   
        },
        {
            "name": "Boulder en Espa\u00f1a",
            "link": [
              "https://amzn.to/3UizeG0", 
                "https://amzn.to/3SiGNuV"
            ],
            "thumbnail": "https://m.media-amazon.com/images/I/81UJX3rkGML._AC_UY218_.jpg"   
        }
    ],
    "country": "es",
    "state": "valencian-community",
	"rock_type": "lime",
	"overview": [
		"Buñol, located in Spain, is renowned for its exquisite limestone boulders and stunning natural surroundings. Climbers flock here for the unique pockets and crimps that offer exciting challenges. Its fame lies in the picturesque landscapes and the pleasant climbing conditions during spring and autumn.",
		"Buñol, situado en España, es conocido por sus exquisitos bloques de piedra caliza y su impresionante entorno natural. Los escaladores acuden aquí en busca de los únicos agujeros y cantos que ofrecen emocionantes desafíos. Su fama radica en los paisajes pintorescos y las agradables condiciones de escalada durante la primavera y el otoño."
	]
}